bitskins/__init__.py
bitskins/client.py
bitskins/streams.py
bitskins_v2-1.0.2.dist-info/METADATA
bitskins_v2-1.0.2.dist-info/WHEEL
bitskins_v2-1.0.2.dist-info/top_level.txt
bitskins_v2-1.0.2.dist-info/RECORD
