Metadata-Version: 2.1
Name: bitskins-v2
Version: 1.0.2
Summary: An unofficial wrapper for the Bitskins V2 API in Python.
Home-page: https://github.com/kasperlindau/bitskins-v2-wrapper
License: UNKNOWN
Keywords: bitskins v2 api rest websockets
Platform: UNKNOWN
